seqexplainer/__init__.py
seqexplainer/_ism.py
seqexplainer/_layer_outs.py
seqexplainer/_utils.py
seqexplainer/attributions/__init__.py
seqexplainer/attributions/_attributions.py
seqexplainer/attributions/_modisco.py
seqexplainer/attributions/_plot.py
seqexplainer/attributions/_references.py
seqexplainer/deprecated/_deprecated.py
seqexplainer/experimental/_experimental.py
seqexplainer/filters/__init__.py
seqexplainer/filters/_activations.py
seqexplainer/filters/_annotate.py
seqexplainer/filters/_motifs.py
seqexplainer/filters/_plot.py
seqexplainer/generative/__init__.py
seqexplainer/generative/_evolution.py
seqexplainer/gia/__init__.py
seqexplainer/gia/_complex_perturb.py
seqexplainer/gia/_gia.py
seqexplainer/gia/_gia_helpers.py
seqexplainer/gia/_null_models.py
seqexplainer/gia/_perturb.py
seqexplainer/preprocess/_helpers.py
seqexplainer/preprocess/_preprocess.py
seqexplainer-0.1.2.dist-info/LICENSE
seqexplainer-0.1.2.dist-info/METADATA
seqexplainer-0.1.2.dist-info/WHEEL
seqexplainer-0.1.2.dist-info/RECORD
