Metadata-Version: 2.1
Name: seqexplainer
Version: 0.1.2
Summary: Interpreting sequence-to-function machine learning models
Author: adamklie
Author-email: aklie@ucsd.edu
Requires-Python: >=3.9,<3.11
Classifier: Programming Language :: Python :: 3
Classifier: Programming Language :: Python :: 3.9
Classifier: Programming Language :: Python :: 3.10
Requires-Dist: captum (==0.5)
Requires-Dist: logomaker (>=0.8,<0.9)
Requires-Dist: modisco-lite (>=2.2.0,<3.0.0)
Requires-Dist: numpy (>=1.23.5,<1.24.0)
Requires-Dist: torch (>=1.12.0)
Requires-Dist: tqdm (>=4.65.0,<5.0.0)
Requires-Dist: yuzu-ism (>=0.0.1,<0.0.2)
